graphql2python/__info__.py
graphql2python/__init__.py
graphql2python/__main__.py
graphql2python/__version__.py
graphql2python/model/__init__.py
graphql2python/model/config.py
graphql2python/model/generate.py
graphql2python/model/render.py
graphql2python/model/templates/comment.jinja2
graphql2python/model/templates/docstring.jinja2
graphql2python/model/templates/enum.jinja2
graphql2python/model/templates/interface.jinja2
graphql2python/model/templates/object.jinja2
graphql2python/model/templates/scalar.jinja2
graphql2python/model/templates/union.jinja2
graphql2python/utils/__init__.py
graphql2python/utils/graphlib.py
graphql2python-0.0.6.dist-info/METADATA
graphql2python-0.0.6.dist-info/WHEEL
graphql2python-0.0.6.dist-info/entry_points.txt
graphql2python-0.0.6.dist-info/top_level.txt
graphql2python-0.0.6.dist-info/RECORD
