Metadata-Version: 2.1
Name: graphql2python
Version: 0.0.6
Summary: Tools for GraphQL client in python.
Home-page: https://github.com/denisart/graphql2python
Author: Denis A. Artyushin
Maintainer: Denis A. Artyushin
Maintainer-email: artyushinden@gmail.com
License: MIT
Platform: UNKNOWN
Requires-Python: >=3.8
Requires-Dist: click (<8.2,>=8.1)
Requires-Dist: graphql-core (<3.3,>=3.2)
Requires-Dist: jinja2 (<3.2,>=3.1)
Requires-Dist: pydantic (<1.11,>=1.10)
Requires-Dist: pyyaml (<6.1,>=6.0)
Provides-Extra: dev
Requires-Dist: furo (<2022.10,>=2022.9) ; extra == 'dev'
Requires-Dist: isort (<5.11,>=5.10) ; extra == 'dev'
Requires-Dist: mypy (<0.992,>=0.991) ; extra == 'dev'
Requires-Dist: pylint-pydantic (<0.2,>=0.1) ; extra == 'dev'
Requires-Dist: pylint (<2.16,>=2.15) ; extra == 'dev'
Requires-Dist: sphinx (<5.4,>=5.3) ; extra == 'dev'
Requires-Dist: types-pyyaml (<6.1,>=6.0) ; extra == 'dev'
Requires-Dist: wheel (<0.39,>=0.38) ; extra == 'dev'
Provides-Extra: test
Requires-Dist: pytest-cov (<3.1,>=3.0) ; extra == 'test'
Requires-Dist: pytest-mock (<3.11,>=3.10) ; extra == 'test'
Requires-Dist: pytest (<7.3,>=7.2) ; extra == 'test'
